__init__.py
injectx/__init__.py
injectx/domain/model/__init__.py
injectx/domain/model/config.py
injectx/domain/model/presentation.py
injectx/domain/model/repository.py
injectx/domain/model/service.py
injectx/presentation/injector.py
inject_x-0.0.0.dist-info/METADATA
inject_x-0.0.0.dist-info/WHEEL
inject_x-0.0.0.dist-info/top_level.txt
inject_x-0.0.0.dist-info/RECORD
