Metadata-Version: 2.2
Name: inject-x
Version: 0.0.0
Summary: Natural language request to json converter library
Author-email: Colageo Mirko <mirko.colageo@gmail.com>
License: MIT License
Project-URL: Homepage, https://github.com/bocejo5/injectx
Project-URL: Documentation, https://github.com/bocejo5/injectx
Project-URL: Repository, https://github.com/bocejo5/injectx
Project-URL: Issues, https://github.com/bocejo5/injectx/issues
Keywords: ioc,dependency injection,inversion of control,automatic class loader
Classifier: Development Status :: 4 - Beta
Classifier: Intended Audience :: Developers
Classifier: Topic :: Software Development :: Libraries
Classifier: Topic :: Software Development :: Build Tools
Classifier: Topic :: Scientific/Engineering :: Artificial Intelligence
Classifier: Programming Language :: Python :: 3
Classifier: Programming Language :: Python :: 3.11
Classifier: Programming Language :: Python :: 3.12
Classifier: License :: OSI Approved :: MIT License
Classifier: Operating System :: OS Independent
Requires-Python: >=3.11.5
Requires-Dist: backports.tarfile==1.2.0
Requires-Dist: build==1.2.2.post1
Requires-Dist: bumpver==2024.1130
Requires-Dist: certifi==2025.1.31
Requires-Dist: cffi==1.17.1
Requires-Dist: charset-normalizer==3.4.1
Requires-Dist: click==8.1.8
Requires-Dist: colorama==0.4.6
Requires-Dist: cryptography==43.0.3
Requires-Dist: docutils==0.21.2
Requires-Dist: id==1.5.0
Requires-Dist: idna==3.10
Requires-Dist: importlib_metadata==8.6.1
Requires-Dist: injector==0.22.0
Requires-Dist: jaraco.classes==3.4.0
Requires-Dist: jaraco.context==6.0.1
Requires-Dist: jaraco.functools==4.1.0
Requires-Dist: jeepney==0.9.0
Requires-Dist: keyring==25.6.0
Requires-Dist: lexid==2021.1006
Requires-Dist: markdown-it-py==3.0.0
Requires-Dist: mdurl==0.1.2
Requires-Dist: more-itertools==10.6.0
Requires-Dist: nh3==0.2.21
Requires-Dist: packaging==24.2
Requires-Dist: pycparser==2.22
Requires-Dist: Pygments==2.19.1
Requires-Dist: pyproject_hooks==1.2.0
Requires-Dist: readme_renderer==44.0
Requires-Dist: requests==2.32.3
Requires-Dist: requests-toolbelt==1.0.0
Requires-Dist: rfc3986==2.0.0
Requires-Dist: rich==13.9.4
Requires-Dist: SecretStorage==3.3.3
Requires-Dist: toml==0.10.2
Requires-Dist: tomli==2.2.1
Requires-Dist: twine==6.1.0
Requires-Dist: typing_extensions==4.12.2
Requires-Dist: urllib3==2.3.0
Requires-Dist: zipp==3.21.0
